{"resource": "model/5b968a782774cb43ca00020d", "error": null, "code": 200, "location": "https://bigml.io/andromeda/model/5b968a782774cb43ca00020d", "object": {"created": "2018-09-10T15:15:04.878000", "range": [1, 2665], "split_candidates": 32, "cluster": null, "shared": false, "configuration_status": false, "out_of_bag": false, "selective_pruning": true, "dataset_field_types": {"categorical": 4, "text": 0, "preferred": 22, "datetime": 0, "numeric": 20, "items": 0, "total": 24, "effective_fields": 24}, "name": "Churn ration fields", "updated": "2018-09-10T15:15:56.946000", "number_of_batchpredictions": 1, "optiml_status": false, "cluster_status": false, "tags": ["bindings example", "dirty churn"], "ensemble": false, "credits": 0, "creator": "merce_demo", "dataset_status": true, "description": "", "name_options": "512-node, pruned, deterministic order", "ordering": 0, "missing_splits": false, "private": true, "size": 402554, "code": 200, "locale": "en_US", "status": {"progress": 1, "message": "The model has been created", "code": 5, "elapsed": 2989}, "configuration": null, "objective_field": "000013", "boosted_ensemble": false, "type": 0, "subscription": false, "dataset": "dataset/5b968a5fc7736e65800002ff", "sample_rate": 1.0, "objective_fields": ["000013"], "category": 0, "optiml": null, "rows": 2665, "columns": 18, "depth_threshold": 512, "number_of_predictions": 1, "number_of_evaluations": 1, "max_rows": 2665, "model": {"kind": "mtree", "model_fields": {"000001": {"name": "Account length", "generated": false, "optype": "numeric", "column_number": 1, "preferred": true, "datatype": "int16"}, "100014": {"name": "Total day charge per call", "generated": true, "optype": "numeric", "column_number": 20, "preferred": true, "datatype": "double"}, "000006": {"name": "Total day minutes", "generated": false, "optype": "numeric", "column_number": 6, "preferred": true, "datatype": "double"}, "000003": {"name": "International plan", "generated": false, "optype": "categorical", "column_number": 3, "preferred": true, "term_analysis": {"enabled": true}, "datatype": "string"}, "000007": {"name": "Total day calls", "generated": false, "optype": "numeric", "column_number": 7, "preferred": true, "datatype": "int16"}, "000005": {"name": "Number vmail messages", "generated": false, "optype": "numeric", "column_number": 5, "preferred": true, "datatype": "int8"}, "100015": {"name": "Total eve charge per call", "generated": true, "optype": "numeric", "column_number": 21, "preferred": true, "datatype": "double"}, "000013": {"name": "Churn", "generated": false, "optype": "categorical", "column_number": 19, "preferred": true, "term_analysis": {"enabled": true}, "datatype": "string"}, "100017": {"name": "Total intl charge per call", "generated": true, "optype": "numeric", "column_number": 23, "preferred": true, "datatype": "double"}, "000012": {"name": "Customer service calls", "generated": false, "optype": "numeric", "column_number": 18, "preferred": true, "datatype": "int8"}, "00000a": {"name": "Total eve calls", "generated": false, "optype": "numeric", "column_number": 10, "preferred": true, "datatype": "int16"}, "100016": {"name": "Total night charge per call", "generated": true, "optype": "numeric", "column_number": 22, "preferred": true, "datatype": "double"}, "00000f": {"name": "Total intl minutes", "generated": false, "optype": "numeric", "column_number": 15, "preferred": true, "datatype": "double"}, "000009": {"name": "Total eve minutes", "generated": false, "optype": "numeric", "column_number": 9, "preferred": true, "datatype": "double"}, "00000d": {"name": "Total night calls", "generated": false, "optype": "numeric", "column_number": 13, "preferred": true, "datatype": "int16"}, "000010": {"name": "Total intl calls", "generated": false, "optype": "numeric", "column_number": 16, "preferred": true, "datatype": "int8"}, "00000c": {"name": "Total night minutes", "generated": false, "optype": "numeric", "column_number": 12, "preferred": true, "datatype": "double"}}, "importance": [["000006", 0.29239], ["000009", 0.13934], ["000012", 0.11697], ["000003", 0.08423], ["100014", 0.06437], ["00000c", 0.05219], ["00000f", 0.05036], ["000005", 0.05013], ["100017", 0.04114], ["000001", 0.0314], ["000007", 0.02973], ["00000a", 0.01134], ["00000d", 0.01104], ["000010", 0.01037], ["100016", 0.00997], ["100015", 0.00502]], "distribution": {"predictions": {"categories": [["False", 2274], ["True", 391]]}, "training": {"categories": [["False", 2268], ["True", 397]]}}, "missing_tokens": ["", "NaN", "NULL", "N/A", "null", "-", "#REF!", "#VALUE!", "?", "#NULL!", "#NUM!", "#DIV/0", "n/a", "#NAME?", "NIL", "nil", "na", "#N/A", "NA"], "root": {"objective_summary": {"categories": [["False", 2268], ["True", 397]]}, "children": [{"objective_summary": {"categories": [["False", 176], ["True", 142]]}, "children": [{"objective_summary": {"categories": [["False", 81], ["True", 5]]}, "children": [{"objective_summary": {"categories": [["False", 76], ["True", 2]]}, "children": [{"objective_summary": {"categories": [["False", 72]]}, "predicate": {"operator": ">", "field": "00000f", "value": 6.975}, "count": 72, "output": "False", "id": 4, "confidence": 0.94935}, {"objective_summary": {"categories": [["False", 4], ["True", 2]]}, "children": [{"objective_summary": {"categories": [["True", 2]]}, "predicate": {"operator": ">", "field": "000005", "value": 30}, "count": 2, "output": "True", "id": 6, "confidence": 0.34237}, {"objective_summary": {"categories": [["False", 4]]}, "predicate": {"operator": "<=", "field": "000005", "value": 30}, "count": 4, "output": "False", "id": 7, "confidence": 0.5101}], "predicate": {"operator": "<=", "field": "00000f", "value": 6.975}, "count": 6, "output": "False", "id": 5, "confidence": 0.29999}], "predicate": {"operator": "=", "field": "000003", "value": "No"}, "count": 78, "output": "False", "id": 3, "confidence": 0.91125}, {"objective_summary": {"categories": [["False", 5], ["True", 3]]}, "children": [{"objective_summary": {"categories": [["False", 5], ["True", 1]]}, "children": [{"objective_summary": {"categories": [["True", 1]]}, "predicate": {"operator": ">", "field": "00000f", "value": 15}, "count": 1, "output": "True", "id": 10, "confidence": 0.20654}, {"objective_summary": {"categories": [["False", 5]]}, "predicate": {"operator": "<=", "field": "00000f", "value": 15}, "count": 5, "output": "False", "id": 11, "confidence": 0.56551}], "predicate": {"operator": ">", "field": "00000c", "value": 170.15}, "count": 6, "output": "False", "id": 9, "confidence": 0.43649}, {"objective_summary": {"categories": [["True", 2]]}, "predicate": {"operator": "<=", "field": "00000c", "value": 170.15}, "count": 2, "output": "True", "id": 12, "confidence": 0.34237}], "predicate": {"operator": "=", "field": "000003", "value": "Yes"}, "count": 8, "output": "False", "id": 8, "confidence": 0.30574}], "predicate": {"operator": ">", "field": "000005", "value": 5}, "count": 86, "output": "False", "id": 2, "confidence": 0.87102}, {"objective_summary": {"categories": [["True", 137], ["False", 95]]}, "children": [{"objective_summary": {"categories": [["True", 103], ["False", 27]]}, "children": [{"objective_summary": {"categories": [["True", 69], ["False", 2]]}, "children": [{"objective_summary": {"categories": [["True", 59]]}, "predicate": {"operator": ">", "field": "00000a", "value": 80}, "count": 59, "output": "True", "id": 16, "confidence": 0.93887}, {"objective_summary": {"categories": [["True", 10], ["False", 2]]}, "children": [{"objective_summary": {"categories": [["True", 9]]}, "predicate": {"operator": ">", "field": "100015", "value": 0.24063}, "count": 9, "output": "True", "id": 18, "confidence": 0.70085}, {"objective_summary": {"categories": [["False", 2], ["True", 1]]}, "children": [{"objective_summary": {"categories": [["False", 2]]}, "predicate": {"operator": ">", "field": "00000c", "value": 193.35}, "count": 2, "output": "False", "id": 20, "confidence": 0.34237}, {"objective_summary": {"categories": [["True", 1]]}, "predicate": {"operator": "<=", "field": "00000c", "value": 193.35}, "count": 1, "output": "True", "id": 21, "confidence": 0.20654}], "predicate": {"operator": "<=", "field": "100015", "value": 0.24063}, "count": 3, "output": "False", "id": 19, "confidence": 0.20765}], "predicate": {"operator": "<=", "field": "00000a", "value": 80}, "count": 12, "output": "True", "id": 17, "confidence": 0.55196}], "predicate": {"operator": ">", "field": "00000c", "value": 189.65417}, "count": 71, "output": "True", "id": 15, "confidence": 0.90298}, {"objective_summary": {"categories": [["True", 34], ["False", 25]]}, "children": [{"objective_summary": {"categories": [["True", 25], ["False", 4]]}, "children": [{"objective_summary": {"categories": [["True", 23]]}, "predicate": {"operator": ">", "field": "00000c", "value": 127}, "count": 23, "output": "True", "id": 24, "confidence": 0.85688}, {"objective_summary": {"categories": [["False", 4], ["True", 2]]}, "children": [{"objective_summary": {"categories": [["False", 4]]}, "predicate": {"operator": ">", "field": "00000d", "value": 93}, "count": 4, "output": "False", "id": 26, "confidence": 0.5101}, {"objective_summary": {"categories": [["True", 2]]}, "predicate": {"operator": "<=", "field": "00000d", "value": 93}, "count": 2, "output": "True", "id": 27, "confidence": 0.34237}], "predicate": {"operator": "<=", "field": "00000c", "value": 127}, "count": 6, "output": "False", "id": 25, "confidence": 0.29999}], "predicate": {"operator": ">", "field": "000006", "value": 264.15}, "count": 29, "output": "True", "id": 23, "confidence": 0.69441}, {"objective_summary": {"categories": [["False", 21], ["True", 9]]}, "children": [{"objective_summary": {"categories": [["True", 8], ["False", 3]]}, "children": [{"objective_summary": {"categories": [["True", 8]]}, "predicate": {"operator": ">", "field": "100016", "value": 0.05021}, "count": 8, "output": "True", "id": 30, "confidence": 0.67558}, {"objective_summary": {"categories": [["False", 3]]}, "predicate": {"operator": "<=", "field": "100016", "value": 0.05021}, "count": 3, "output": "False", "id": 31, "confidence": 0.43849}], "predicate": {"operator": ">", "field": "000009", "value": 242.4}, "count": 11, "output": "True", "id": 29, "confidence": 0.43435}, {"objective_summary": {"categories": [["False", 18], ["True", 1]]}, "children": [{"objective_summary": {"categories": [["True", 1]]}, "predicate": {"operator": ">", "field": "100015", "value": 0.26857}, "count": 1, "output": "True", "id": 33, "confidence": 0.20654}, {"objective_summary": {"categories": [["False", 18]]}, "predicate": {"operator": "<=", "field": "100015", "value": 0.26857}, "count": 18, "output": "False", "id": 34, "confidence": 0.82412}], "predicate": {"operator": "<=", "field": "000009", "value": 242.4}, "count": 19, "output": "False", "id": 32, "confidence": 0.75361}], "predicate": {"operator": "<=", "field": "000006", "value": 264.15}, "count": 30, "output": "False", "id": 28, "confidence": 0.52124}], "predicate": {"operator": "<=", "field": "00000c", "value": 189.65417}, "count": 59, "output": "True", "id": 22, "confidence": 0.44934}], "predicate": {"operator": ">", "field": "000009", "value": 199.2035}, "count": 130, "output": "True", "id": 14, "confidence": 0.71468}, {"objective_summary": {"categories": [["False", 68], ["True", 34]]}, "children": [{"objective_summary": {"categories": [["True", 18], ["False", 7]]}, "children": [{"objective_summary": {"categories": [["True", 18], ["False", 2]]}, "children": [{"objective_summary": {"categories": [["True", 17]]}, "predicate": {"operator": ">", "field": "00000c", "value": 146}, "count": 17, "output": "True", "id": 38, "confidence": 0.81568}, {"objective_summary": {"categories": [["False", 2], ["True", 1]]}, "children": [{"objective_summary": {"categories": [["False", 2]]}, "predicate": {"operator": ">", "field": "100017", "value": 0.42571}, "count": 2, "output": "False", "id": 40, "confidence": 0.34237}, {"objective_summary": {"categories": [["True", 1]]}, "predicate": {"operator": "<=", "field": "100017", "value": 0.42571}, "count": 1, "output": "True", "id": 41, "confidence": 0.20654}], "predicate": {"operator": "<=", "field": "00000c", "value": 146}, "count": 3, "output": "False", "id": 39, "confidence": 0.20765}], "predicate": {"operator": ">", "field": "000009", "value": 144.35}, "count": 20, "output": "True", "id": 37, "confidence": 0.69896}, {"objective_summary": {"categories": [["False", 5]]}, "predicate": {"operator": "<=", "field": "000009", "value": 144.35}, "count": 5, "output": "False", "id": 42, "confidence": 0.56551}], "predicate": {"operator": ">", "field": "000006", "value": 282.55}, "count": 25, "output": "True", "id": 36, "confidence": 0.52423}, {"objective_summary": {"categories": [["False", 61], ["True", 16]]}, "children": [{"objective_summary": {"categories": [["False", 24], ["True", 15]]}, "children": [{"objective_summary": {"categories": [["True", 4]]}, "predicate": {"operator": ">", "field": "00000f", "value": 12.05}, "count": 4, "output": "True", "id": 45, "confidence": 0.5101}, {"objective_summary": {"categories": [["False", 24], ["True", 11]]}, "children": [{"objective_summary": {"categories": [["True", 4]]}, "predicate": {"operator": ">", "field": "000006", "value": 275.55}, "count": 4, "output": "True", "id": 47, "confidence": 0.5101}, {"objective_summary": {"categories": [["False", 24], ["True", 7]]}, "children": [{"objective_summary": {"categories": [["True", 5], ["False", 4]]}, "children": [{"objective_summary": {"categories": [["True", 4]]}, "predicate": {"operator": ">", "field": "000009", "value": 183.75}, "count": 4, "output": "True", "id": 50, "confidence": 0.5101}, {"objective_summary": {"categories": [["False", 4], ["True", 1]]}, "children": [{"objective_summary": {"categories": [["False", 4]]}, "predicate": {"operator": ">", "field": "00000c", "value": 199.2}, "count": 4, "output": "False", "id": 52, "confidence": 0.5101}, {"objective_summary": {"categories": [["True", 1]]}, "predicate": {"operator": "<=", "field": "00000c", "value": 199.2}, "count": 1, "output": "True", "id": 53, "confidence": 0.20654}], "predicate": {"operator": "<=", "field": "000009", "value": 183.75}, "count": 5, "output": "False", "id": 51, "confidence": 0.37553}], "predicate": {"operator": ">", "field": "000007", "value": 113}, "count": 9, "output": "True", "id": 49, "confidence": 0.26665}, {"objective_summary": {"categories": [["False", 20], ["True", 2]]}, "children": [{"objective_summary": {"categories": [["True", 2]]}, "predicate": {"operator": ">", "field": "00000c", "value": 290.55}, "count": 2, "output": "True", "id": 55, "confidence": 0.34237}, {"objective_summary": {"categories": [["False", 20]]}, "predicate": {"operator": "<=", "field": "00000c", "value": 290.55}, "count": 20, "output": "False", "id": 56, "confidence": 0.83887}], "predicate": {"operator": "<=", "field": "000007", "value": 113}, "count": 22, "output": "False", "id": 54, "confidence": 0.72185}], "predicate": {"operator": "<=", "field": "000006", "value": 275.55}, "count": 31, "output": "False", "id": 48, "confidence": 0.60187}], "predicate": {"operator": "<=", "field": "00000f", "value": 12.05}, "count": 35, "output": "False", "id": 46, "confidence": 0.5202}], "predicate": {"operator": ">", "field": "00000c", "value": 188.4125}, "count": 39, "output": "False", "id": 44, "confidence": 0.45899}, {"objective_summary": {"categories": [["False", 37], ["True", 1]]}, "children": [{"objective_summary": {"categories": [["False", 34]]}, "predicate": {"operator": ">", "field": "000006", "value": 246.85}, "count": 34, "output": "False", "id": 58, "confidence": 0.89848}, {"objective_summary": {"categories": [["False", 3], ["True", 1]]}, "children": [{"objective_summary": {"categories": [["True", 1]]}, "predicate": {"operator": ">", "field": "00000f", "value": 11.4}, "count": 1, "output": "True", "id": 60, "confidence": 0.20654}, {"objective_summary": {"categories": [["False", 3]]}, "predicate": {"operator": "<=", "field": "00000f", "value": 11.4}, "count": 3, "output": "False", "id": 61, "confidence": 0.43849}], "predicate": {"operator": "<=", "field": "000006", "value": 246.85}, "count": 4, "output": "False", "id": 59, "confidence": 0.30064}], "predicate": {"operator": "<=", "field": "00000c", "value": 188.4125}, "count": 38, "output": "False", "id": 57, "confidence": 0.86505}], "predicate": {"operator": "<=", "field": "000006", "value": 282.55}, "count": 77, "output": "False", "id": 43, "confidence": 0.68879}], "predicate": {"operator": "<=", "field": "000009", "value": 199.2035}, "count": 102, "output": "False", "id": 35, "confidence": 0.5706}], "predicate": {"operator": "<=", "field": "000005", "value": 5}, "count": 232, "output": "True", "id": 13, "confidence": 0.52627}], "predicate": {"operator": ">", "field": "000006", "value": 244.67063}, "count": 318, "output": "False", "id": 1, "confidence": 0.4985}, {"objective_summary": {"categories": [["False", 2092], ["True", 255]]}, "children": [{"objective_summary": {"categories": [["True", 105], ["False", 90]]}, "children": [{"objective_summary": {"categories": [["False", 76], ["True", 25]]}, "children": [{"objective_summary": {"categories": [["False", 70], ["True", 12]]}, "children": [{"objective_summary": {"categories": [["False", 60], ["True", 5]]}, "children": [{"objective_summary": {"categories": [["False", 58], ["True", 2]]}, "children": [{"objective_summary": {"categories": [["False", 19], ["True", 2]]}, "children": [{"objective_summary": {"categories": [["True", 1]]}, "predicate": {"operator": ">", "field": "00000d", "value": 120}, "count": 1, "output": "True", "id": 69, "confidence": 0.20654}, {"objective_summary": {"categories": [["False", 19], ["True", 1]]}, "predicate": {"operator": "<=", "field": "00000d", "value": 120}, "count": 20, "output": "False", "id": 70, "confidence": 0.76386}], "predicate": {"operator": ">", "field": "000001", "value": 119}, "count": 21, "output": "False", "id": 68, "confidence": 0.71085}, {"objective_summary": {"categories": [["False", 39]]}, "predicate": {"operator": "<=", "field": "000001", "value": 119}, "count": 39, "output": "False", "id": 71, "confidence": 0.91033}], "predicate": {"operator": "=", "field": "000003", "value": "No"}, "count": 60, "output": "False", "id": 67, "confidence": 0.88636}, {"objective_summary": {"categories": [["True", 3], ["False", 2]]}, "children": [{"objective_summary": {"categories": [["True", 3]]}, "predicate": {"operator": ">", "field": "100017", "value": 0.796}, "count": 3, "output": "True", "id": 73, "confidence": 0.43849}, {"objective_summary": {"categories": [["False", 2]]}, "predicate": {"operator": "<=", "field": "100017", "value": 0.796}, "count": 2, "output": "False", "id": 74, "confidence": 0.34237}], "predicate": {"operator": "=", "field": "000003", "value": "Yes"}, "count": 5, "output": "True", "id": 72, "confidence": 0.23072}], "predicate": {"operator": ">", "field": "000006", "value": 173.6375}, "count": 65, "output": "False", "id": 66, "confidence": 0.83224}, {"objective_summary": {"categories": [["False", 10], ["True", 7]]}, "children": [{"objective_summary": {"categories": [["False", 10]]}, "predicate": {"operator": ">", "field": "000009", "value": 209.1}, "count": 10, "output": "False", "id": 76, "confidence": 0.72246}, {"objective_summary": {"categories": [["True", 7]]}, "predicate": {"operator": "<=", "field": "000009", "value": 209.1}, "count": 7, "output": "True", "id": 77, "confidence": 0.64566}], "predicate": {"operator": "<=", "field": "000006", "value": 173.6375}, "count": 17, "output": "False", "id": 75, "confidence": 0.36005}], "predicate": {"operator": ">", "field": "000009", "value": 152.15}, "count": 82, "output": "False", "id": 65, "confidence": 0.7614}, {"objective_summary": {"categories": [["True", 13], ["False", 6]]}, "children": [{"objective_summary": {"categories": [["False", 6], ["True", 4]]}, "children": [{"objective_summary": {"categories": [["False", 5]]}, "predicate": {"operator": ">", "field": "000009", "value": 134.55}, "count": 5, "output": "False", "id": 80, "confidence": 0.56551}, {"objective_summary": {"categories": [["True", 4], ["False", 1]]}, "children": [{"objective_summary": {"categories": [["False", 1]]}, "predicate": {"operator": ">", "field": "00000f", "value": 11.2}, "count": 1, "output": "False", "id": 82, "confidence": 0.20654}, {"objective_summary": {"categories": [["True", 4]]}, "predicate": {"operator": "<=", "field": "00000f", "value": 11.2}, "count": 4, "output": "True", "id": 83, "confidence": 0.5101}], "predicate": {"operator": "<=", "field": "000009", "value": 134.55}, "count": 5, "output": "True", "id": 81, "confidence": 0.37553}], "predicate": {"operator": ">", "field": "100014", "value": 0.31896}, "count": 10, "output": "False", "id": 79, "confidence": 0.31267}, {"objective_summary": {"categories": [["True", 9]]}, "predicate": {"operator": "<=", "field": "100014", "value": 0.31896}, "count": 9, "output": "True", "id": 84, "confidence": 0.70085}], "predicate": {"operator": "<=", "field": "000009", "value": 152.15}, "count": 19, "output": "True", "id": 78, "confidence": 0.4601}], "predicate": {"operator": ">", "field": "000006", "value": 164.14591}, "count": 101, "output": "False", "id": 64, "confidence": 0.6601}, {"objective_summary": {"categories": [["True", 80], ["False", 14]]}, "children": [{"objective_summary": {"categories": [["True", 40], ["False", 14]]}, "children": [{"objective_summary": {"categories": [["True", 18], ["False", 14]]}, "children": [{"objective_summary": {"categories": [["False", 14], ["True", 10]]}, "children": [{"objective_summary": {"categories": [["False", 13], ["True", 3]]}, "children": [{"objective_summary": {"categories": [["False", 10]]}, "predicate": {"operator": ">", "field": "000001", "value": 97}, "count": 10, "output": "False", "id": 90, "confidence": 0.72246}, {"objective_summary": {"categories": [["False", 3], ["True", 3]]}, "children": [{"objective_summary": {"categories": [["True", 3]]}, "predicate": {"operator": ">", "field": "000001", "value": 76}, "count": 3, "output": "True", "id": 92, "confidence": 0.43849}, {"objective_summary": {"categories": [["False", 3]]}, "predicate": {"operator": "<=", "field": "000001", "value": 76}, "count": 3, "output": "False", "id": 93, "confidence": 0.43849}], "predicate": {"operator": "<=", "field": "000001", "value": 97}, "count": 6, "output": "False", "id": 91, "confidence": 0.18761}], "predicate": {"operator": ">", "field": "000006", "value": 135.8}, "count": 16, "output": "False", "id": 89, "confidence": 0.56991}, {"objective_summary": {"categories": [["True", 7], ["False", 1]]}, "children": [{"objective_summary": {"categories": [["False", 1]]}, "predicate": {"operator": ">", "field": "100015", "value": 0.30856}, "count": 1, "output": "False", "id": 95, "confidence": 0.20654}, {"objective_summary": {"categories": [["True", 7]]}, "predicate": {"operator": "<=", "field": "100015", "value": 0.30856}, "count": 7, "output": "True", "id": 96, "confidence": 0.64566}], "predicate": {"operator": "<=", "field": "000006", "value": 135.8}, "count": 8, "output": "True", "id": 94, "confidence": 0.52911}], "predicate": {"operator": ">", "field": "00000c", "value": 159.45}, "count": 24, "output": "False", "id": 88, "confidence": 0.38834}, {"objective_summary": {"categories": [["True", 8]]}, "predicate": {"operator": "<=", "field": "00000c", "value": 159.45}, "count": 8, "output": "True", "id": 97, "confidence": 0.67558}], "predicate": {"operator": ">", "field": "000009", "value": 189.3}, "count": 32, "output": "True", "id": 87, "confidence": 0.39325}, {"objective_summary": {"categories": [["True", 22]]}, "predicate": {"operator": "<=", "field": "000009", "value": 189.3}, "count": 22, "output": "True", "id": 98, "confidence": 0.85134}], "predicate": {"operator": ">", "field": "100014", "value": 0.21199}, "count": 54, "output": "True", "id": 86, "confidence": 0.61069}, {"objective_summary": {"categories": [["True", 39]]}, "predicate": {"operator": "<=", "field": "100014", "value": 0.21199}, "count": 39, "output": "True", "id": 99, "confidence": 0.91033}], "predicate": {"operator": "<=", "field": "000006", "value": 164.14591}, "count": 94, "output": "True", "id": 85, "confidence": 0.7654}], "predicate": {"operator": ">", "field": "000012", "value": 3}, "count": 195, "output": "True", "id": 63, "confidence": 0.46842}, {"objective_summary": {"categories": [["False", 2002], ["True", 150]]}, "children": [{"objective_summary": {"categories": [["False", 1881], ["True", 72]]}, "children": [{"objective_summary": {"categories": [["False", 207], ["True", 29]]}, "children": [{"objective_summary": {"categories": [["True", 15], ["False", 6]]}, "children": [{"objective_summary": {"categories": [["False", 5]]}, "predicate": {"operator": ">", "field": "000005", "value": 12}, "count": 5, "output": "False", "id": 104, "confidence": 0.56551}, {"objective_summary": {"categories": [["True", 15], ["False", 1]]}, "children": [{"objective_summary": {"categories": [["True", 15]]}, "predicate": {"operator": ">", "field": "00000f", "value": 2.75}, "count": 15, "output": "True", "id": 106, "confidence": 0.79611}, {"objective_summary": {"categories": [["False", 1]]}, "predicate": {"operator": "<=", "field": "00000f", "value": 2.75}, "count": 1, "output": "False", "id": 107, "confidence": 0.20654}], "predicate": {"operator": "<=", "field": "000005", "value": 12}, "count": 16, "output": "True", "id": 105, "confidence": 0.71671}], "predicate": {"operator": ">", "field": "000009", "value": 271.56099}, "count": 21, "output": "True", "id": 103, "confidence": 0.50043}, {"objective_summary": {"categories": [["False", 201], ["True", 14]]}, "children": [{"objective_summary": {"categories": [["False", 25], ["True", 6]]}, "children": [{"objective_summary": {"categories": [["True", 6], ["False", 5]]}, "children": [{"objective_summary": {"categories": [["True", 4]]}, "predicate": {"operator": ">", "field": "100017", "value": 0.83875}, "count": 4, "output": "True", "id": 111, "confidence": 0.5101}, {"objective_summary": {"categories": [["False", 5], ["True", 2]]}, "children": [{"objective_summary": {"categories": [["False", 5]]}, "predicate": {"operator": ">", "field": "100017", "value": 0.484}, "count": 5, "output": "False", "id": 113, "confidence": 0.56551}, {"objective_summary": {"categories": [["True", 2]]}, "predicate": {"operator": "<=", "field": "100017", "value": 0.484}, "count": 2, "output": "True", "id": 114, "confidence": 0.34237}], "predicate": {"operator": "<=", "field": "100017", "value": 0.83875}, "count": 7, "output": "False", "id": 112, "confidence": 0.35893}], "predicate": {"operator": ">", "field": "000001", "value": 121}, "count": 11, "output": "True", "id": 110, "confidence": 0.28009}, {"objective_summary": {"categories": [["False", 20]]}, "predicate": {"operator": "<=", "field": "000001", "value": 121}, "count": 20, "output": "False", "id": 115, "confidence": 0.83887}], "predicate": {"operator": ">", "field": "000009", "value": 244.6}, "count": 31, "output": "False", "id": 109, "confidence": 0.63719}, {"objective_summary": {"categories": [["False", 176], ["True", 8]]}, "children": [{"objective_summary": {"categories": [["False", 53]]}, "predicate": {"operator": ">", "field": "000007", "value": 110}, "count": 53, "output": "False", "id": 117, "confidence": 0.93242}, {"objective_summary": {"categories": [["False", 123], ["True", 8]]}, "children": [{"objective_summary": {"categories": [["False", 42]]}, "predicate": {"operator": ">", "field": "00000f", "value": 11.6775}, "count": 42, "output": "False", "id": 119, "confidence": 0.9162}, {"objective_summary": {"categories": [["False", 81], ["True", 8]]}, "children": [{"objective_summary": {"categories": [["False", 15], ["True", 6]]}, "children": [{"objective_summary": {"categories": [["False", 6], ["True", 6]]}, "children": [{"objective_summary": {"categories": [["True", 6], ["False", 2]]}, "children": [{"objective_summary": {"categories": [["False", 2], ["True", 1]]}, "children": [{"objective_summary": {"categories": [["False", 2]]}, "predicate": {"operator": ">", "field": "00000c", "value": 237.45}, "count": 2, "output": "False", "id": 125, "confidence": 0.34237}, {"objective_summary": {"categories": [["True", 1]]}, "predicate": {"operator": "<=", "field": "00000c", "value": 237.45}, "count": 1, "output": "True", "id": 126, "confidence": 0.20654}], "predicate": {"operator": ">", "field": "000009", "value": 214.55}, "count": 3, "output": "False", "id": 124, "confidence": 0.20765}, {"objective_summary": {"categories": [["True", 5]]}, "predicate": {"operator": "<=", "field": "000009", "value": 214.55}, "count": 5, "output": "True", "id": 127, "confidence": 0.56551}], "predicate": {"operator": ">", "field": "000006", "value": 225.6}, "count": 8, "output": "True", "id": 123, "confidence": 0.40927}, {"objective_summary": {"categories": [["False", 4]]}, "predicate": {"operator": "<=", "field": "000006", "value": 225.6}, "count": 4, "output": "False", "id": 128, "confidence": 0.5101}], "predicate": {"operator": ">", "field": "000009", "value": 167.2}, "count": 12, "output": "False", "id": 122, "confidence": 0.25378}, {"objective_summary": {"categories": [["False", 9]]}, "predicate": {"operator": "<=", "field": "000009", "value": 167.2}, "count": 9, "output": "False", "id": 129, "confidence": 0.70085}], "predicate": {"operator": ">", "field": "00000f", "value": 10.455}, "count": 21, "output": "False", "id": 121, "confidence": 0.50043}, {"objective_summary": {"categories": [["False", 66], ["True", 2]]}, "children": [{"objective_summary": {"categories": [["False", 62]]}, "predicate": {"operator": ">", "field": "000009", "value": 136.2}, "count": 62, "output": "False", "id": 131, "confidence": 0.94165}, {"objective_summary": {"categories": [["False", 4], ["True", 2]]}, "children": [{"objective_summary": {"categories": [["True", 2]]}, "predicate": {"operator": ">", "field": "100015", "value": 0.09923}, "count": 2, "output": "True", "id": 133, "confidence": 0.34237}, {"objective_summary": {"categories": [["False", 4]]}, "predicate": {"operator": "<=", "field": "100015", "value": 0.09923}, "count": 4, "output": "False", "id": 134, "confidence": 0.5101}], "predicate": {"operator": "<=", "field": "000009", "value": 136.2}, "count": 6, "output": "False", "id": 132, "confidence": 0.29999}], "predicate": {"operator": "<=", "field": "00000f", "value": 10.455}, "count": 68, "output": "False", "id": 130, "confidence": 0.89895}], "predicate": {"operator": "<=", "field": "00000f", "value": 11.6775}, "count": 89, "output": "False", "id": 120, "confidence": 0.83254}], "predicate": {"operator": "<=", "field": "000007", "value": 110}, "count": 131, "output": "False", "id": 118, "confidence": 0.88412}], "predicate": {"operator": "<=", "field": "000009", "value": 244.6}, "count": 184, "output": "False", "id": 116, "confidence": 0.91656}], "predicate": {"operator": "<=", "field": "000009", "value": 271.56099}, "count": 215, "output": "False", "id": 108, "confidence": 0.89368}], "predicate": {"operator": ">", "field": "000006", "value": 220.03228}, "count": 236, "output": "False", "id": 102, "confidence": 0.82909}, {"objective_summary": {"categories": [["False", 1674], ["True", 43]]}, "children": [{"objective_summary": {"categories": [["False", 1206], ["True", 39]]}, "children": [{"objective_summary": {"categories": [["False", 8], ["True", 3]]}, "children": [{"objective_summary": {"categories": [["True", 3]]}, "predicate": {"operator": ">", "field": "00000c", "value": 230.9}, "count": 3, "output": "True", "id": 138, "confidence": 0.43849}, {"objective_summary": {"categories": [["False", 8]]}, "predicate": {"operator": "<=", "field": "00000c", "value": 230.9}, "count": 8, "output": "False", "id": 139, "confidence": 0.67558}], "predicate": {"operator": ">", "field": "000009", "value": 328.87333}, "count": 11, "output": "False", "id": 137, "confidence": 0.43435}, {"objective_summary": {"categories": [["False", 1198], ["True", 36]]}, "children": [{"objective_summary": {"categories": [["False", 1092], ["True", 36]]}, "children": [{"objective_summary": {"categories": [["False", 1003], ["True", 36]]}, "children": [{"objective_summary": {"categories": [["False", 934], ["True", 29]]}, "children": [{"objective_summary": {"categories": [["False", 68], ["True", 6]]}, "children": [{"objective_summary": {"categories": [["False", 28], ["True", 6]]}, "children": [{"objective_summary": {"categories": [["False", 15]]}, "predicate": {"operator": ">", "field": "000009", "value": 219.3}, "count": 15, "output": "False", "id": 146, "confidence": 0.79611}, {"objective_summary": {"categories": [["False", 13], ["True", 6]]}, "children": [{"objective_summary": {"categories": [["True", 6], ["False", 4]]}, "children": [{"objective_summary": {"categories": [["False", 4], ["True", 2]]}, "children": [{"objective_summary": {"categories": [["True", 2], ["False", 1]]}, "children": [{"objective_summary": {"categories": [["True", 2]]}, "predicate": {"operator": ">", "field": "00000c", "value": 151.5}, "count": 2, "output": "True", "id": 151, "confidence": 0.34237}, {"objective_summary": {"categories": [["False", 1]]}, "predicate": {"operator": "<=", "field": "00000c", "value": 151.5}, "count": 1, "output": "False", "id": 152, "confidence": 0.20654}], "predicate": {"operator": ">", "field": "00000f", "value": 12.25}, "count": 3, "output": "True", "id": 150, "confidence": 0.20765}, {"objective_summary": {"categories": [["False", 3]]}, "predicate": {"operator": "<=", "field": "00000f", "value": 12.25}, "count": 3, "output": "False", "id": 153, "confidence": 0.43849}], "predicate": {"operator": ">", "field": "100017", "value": 0.43087}, "count": 6, "output": "False", "id": 149, "confidence": 0.29999}, {"objective_summary": {"categories": [["True", 4]]}, "predicate": {"operator": "<=", "field": "100017", "value": 0.43087}, "count": 4, "output": "True", "id": 154, "confidence": 0.5101}], "predicate": {"operator": ">", "field": "000009", "value": 199}, "count": 10, "output": "True", "id": 148, "confidence": 0.31267}, {"objective_summary": {"categories": [["False", 9]]}, "predicate": {"operator": "<=", "field": "000009", "value": 199}, "count": 9, "output": "False", "id": 155, "confidence": 0.70085}], "predicate": {"operator": "<=", "field": "000009", "value": 219.3}, "count": 19, "output": "False", "id": 147, "confidence": 0.4601}], "predicate": {"operator": ">", "field": "000010", "value": 4}, "count": 34, "output": "False", "id": 145, "confidence": 0.66486}, {"objective_summary": {"categories": [["False", 40]]}, "predicate": {"operator": "<=", "field": "000010", "value": 4}, "count": 40, "output": "False", "id": 156, "confidence": 0.91238}], "predicate": {"operator": ">", "field": "000007", "value": 125}, "count": 74, "output": "False", "id": 144, "confidence": 0.83418}, {"objective_summary": {"categories": [["False", 866], ["True", 23]]}, "children": [{"objective_summary": {"categories": [["False", 690], ["True", 23]]}, "children": [{"objective_summary": {"categories": [["True", 1]]}, "predicate": {"operator": ">", "field": "000001", "value": 217}, "count": 1, "output": "True", "id": 159, "confidence": 0.20654}, {"objective_summary": {"categories": [["False", 690], ["True", 22]]}, "children": [{"objective_summary": {"categories": [["False", 605], ["True", 22]]}, "children": [{"objective_summary": {"categories": [["False", 38], ["True", 5]]}, "children": [{"objective_summary": {"categories": [["False", 37], ["True", 2]]}, "children": [{"objective_summary": {"categories": [["False", 37], ["True", 1]]}, "children": [{"objective_summary": {"categories": [["False", 35]]}, "predicate": {"operator": ">", "field": "00000f", "value": 8.6}, "count": 35, "output": "False", "id": 165, "confidence": 0.9011}, {"objective_summary": {"categories": [["False", 2], ["True", 1]]}, "children": [{"objective_summary": {"categories": [["True", 1]]}, "predicate": {"operator": ">", "field": "00000f", "value": 8.3}, "count": 1, "output": "True", "id": 167, "confidence": 0.20654}, {"objective_summary": {"categories": [["False", 2]]}, "predicate": {"operator": "<=", "field": "00000f", "value": 8.3}, "count": 2, "output": "False", "id": 168, "confidence": 0.34237}], "predicate": {"operator": "<=", "field": "00000f", "value": 8.6}, "count": 3, "output": "False", "id": 166, "confidence": 0.20765}], "predicate": {"operator": ">", "field": "100015", "value": 0.12112}, "count": 38, "output": "False", "id": 164, "confidence": 0.86505}, {"objective_summary": {"categories": [["True", 1]]}, "predicate": {"operator": "<=", "field": "100015", "value": 0.12112}, "count": 1, "output": "True", "id": 169, "confidence": 0.20654}], "predicate": {"operator": ">", "field": "00000a", "value": 73}, "count": 39, "output": "False", "id": 163, "confidence": 0.83114}, {"objective_summary": {"categories": [["True", 3], ["False", 1]]}, "children": [{"objective_summary": {"categories": [["True", 3]]}, "predicate": {"operator": ">", "field": "00000c", "value": 188.4}, "count": 3, "output": "True", "id": 171, "confidence": 0.43849}, {"objective_summary": {"categories": [["False", 1]]}, "predicate": {"operator": "<=", "field": "00000c", "value": 188.4}, "count": 1, "output": "False", "id": 172, "confidence": 0.20654}], "predicate": {"operator": "<=", "field": "00000a", "value": 73}, "count": 4, "output": "True", "id": 170, "confidence": 0.30064}], "predicate": {"operator": ">", "field": "000006", "value": 212.11778}, "count": 43, "output": "False", "id": 162, "confidence": 0.75521}, {"objective_summary": {"categories": [["False", 567], ["True", 17]]}, "children": [{"objective_summary": {"categories": [["False", 75]]}, "predicate": {"operator": ">", "field": "000009", "value": 264.22054}, "count": 75, "output": "False", "id": 174, "confidence": 0.95127}, {"objective_summary": {"categories": [["False", 492], ["True", 17]]}, "children": [{"objective_summary": {"categories": [["False", 1], ["True", 1]]}, "children": [{"objective_summary": {"categories": [["True", 1]]}, "predicate": {"operator": ">", "field": "00000c", "value": 222.2}, "count": 1, "output": "True", "id": 177, "confidence": 0.20654}, {"objective_summary": {"categories": [["False", 1]]}, "predicate": {"operator": "<=", "field": "00000c", "value": 222.2}, "count": 1, "output": "False", "id": 178, "confidence": 0.20654}], "predicate": {"operator": ">", "field": "000005", "value": 43}, "count": 2, "output": "False", "id": 176, "confidence": 0.09453}, {"objective_summary": {"categories": [["False", 491], ["True", 16]]}, "children": [{"objective_summary": {"categories": [["False", 52]]}, "predicate": {"operator": ">", "field": "100014", "value": 0.41528}, "count": 52, "output": "False", "id": 180, "confidence": 0.93121}, {"objective_summary": {"categories": [["False", 439], ["True", 16]]}, "children": [{"objective_summary": {"categories": [["False", 5], ["True", 2]]}, "children": [{"objective_summary": {"categories": [["False", 5]]}, "predicate": {"operator": ">", "field": "100015", "value": 0.16829}, "count": 5, "output": "False", "id": 183, "confidence": 0.56551}, {"objective_summary": {"categories": [["True", 2]]}, "predicate": {"operator": "<=", "field": "100015", "value": 0.16829}, "count": 2, "output": "True", "id": 184, "confidence": 0.34237}], "predicate": {"operator": ">", "field": "100014", "value": 0.39172}, "count": 7, "output": "False", "id": 182, "confidence": 0.35893}, {"objective_summary": {"categories": [["False", 434], ["True", 14]]}, "children": [{"objective_summary": {"categories": [["False", 69]]}, "predicate": {"operator": ">", "field": "100016", "value": 0.12693}, "count": 69, "output": "False", "id": 186, "confidence": 0.94726}, {"objective_summary": {"categories": [["False", 365], ["True", 14]]}, "children": [{"objective_summary": {"categories": [["False", 311], ["True", 14]]}, "children": [{"objective_summary": {"categories": [["False", 136], ["True", 10]]}, "children": [{"objective_summary": {"categories": [["False", 135], ["True", 8]]}, "children": [{"objective_summary": {"categories": [["False", 31]]}, "predicate": {"operator": ">", "field": "00000d", "value": 119}, "count": 31, "output": "False", "id": 191, "confidence": 0.88974}, {"objective_summary": {"categories": [["False", 104], ["True", 8]]}, "children": [{"objective_summary": {"categories": [["False", 6], ["True", 3]]}, "children": [{"objective_summary": {"categories": [["False", 5]]}, "predicate": {"operator": ">", "field": "00000c", "value": 203.8}, "count": 5, "output": "False", "id": 194, "confidence": 0.56551}, {"objective_summary": {"categories": [["True", 3], ["False", 1]]}, "children": [{"objective_summary": {"categories": [["True", 3]]}, "predicate": {"operator": ">", "field": "00000c", "value": 147.1}, "count": 3, "output": "True", "id": 196, "confidence": 0.43849}, {"objective_summary": {"categories": [["False", 1]]}, "predicate": {"operator": "<=", "field": "00000c", "value": 147.1}, "count": 1, "output": "False", "id": 197, "confidence": 0.20654}], "predicate": {"operator": "<=", "field": "00000c", "value": 203.8}, "count": 4, "output": "True", "id": 195, "confidence": 0.30064}], "predicate": {"operator": ">", "field": "00000d", "value": 115}, "count": 9, "output": "False", "id": 193, "confidence": 0.3542}, {"objective_summary": {"categories": [["False", 98], ["True", 5]]}, "children": [{"objective_summary": {"categories": [["False", 65], ["True", 5]]}, "children": [{"objective_summary": {"categories": [["True", 2], ["False", 1]]}, "children": [{"objective_summary": {"categories": [["True", 2]]}, "predicate": {"operator": ">", "field": "00000c", "value": 185.9}, "count": 2, "output": "True", "id": 201, "confidence": 0.34237}, {"objective_summary": {"categories": [["False", 1]]}, "predicate": {"operator": "<=", "field": "00000c", "value": 185.9}, "count": 1, "output": "False", "id": 202, "confidence": 0.20654}], "predicate": {"operator": ">", "field": "00000a", "value": 133}, "count": 3, "output": "True", "id": 200, "confidence": 0.20765}, {"objective_summary": {"categories": [["False", 64], ["True", 3]]}, "children": [{"objective_summary": {"categories": [["False", 37]]}, "predicate": {"operator": ">", "field": "00000a", "value": 92}, "count": 37, "output": "False", "id": 204, "confidence": 0.90594}, {"objective_summary": {"categories": [["False", 27], ["True", 3]]}, "children": [{"objective_summary": {"categories": [["True", 1]]}, "predicate": {"operator": ">", "field": "000006", "value": 209.25}, "count": 1, "output": "True", "id": 206, "confidence": 0.20654}, {"objective_summary": {"categories": [["False", 27], ["True", 2]]}, "children": [{"objective_summary": {"categories": [["False", 23]]}, "predicate": {"operator": ">", "field": "000007", "value": 85}, "count": 23, "output": "False", "id": 208, "confidence": 0.85688}, {"objective_summary": {"categories": [["False", 4], ["True", 2]]}, "children": [{"objective_summary": {"categories": [["True", 2]]}, "predicate": {"operator": ">", "field": "000005", "value": 9}, "count": 2, "output": "True", "id": 210, "confidence": 0.34237}, {"objective_summary": {"categories": [["False", 4]]}, "predicate": {"operator": "<=", "field": "000005", "value": 9}, "count": 4, "output": "False", "id": 211, "confidence": 0.5101}], "predicate": {"operator": "<=", "field": "000007", "value": 85}, "count": 6, "output": "False", "id": 209, "confidence": 0.29999}], "predicate": {"operator": "<=", "field": "000006", "value": 209.25}, "count": 29, "output": "False", "id": 207, "confidence": 0.78035}], "predicate": {"operator": "<=", "field": "00000a", "value": 92}, "count": 30, "output": "False", "id": 205, "confidence": 0.74379}], "predicate": {"operator": "<=", "field": "00000a", "value": 133}, "count": 67, "output": "False", "id": 203, "confidence": 0.87642}], "predicate": {"operator": ">", "field": "00000f", "value": 10.30333}, "count": 70, "output": "False", "id": 199, "confidence": 0.84344}, {"objective_summary": {"categories": [["False", 33]]}, "predicate": {"operator": "<=", "field": "00000f", "value": 10.30333}, "count": 33, "output": "False", "id": 212, "confidence": 0.89573}], "predicate": {"operator": "<=", "field": "00000d", "value": 115}, "count": 103, "output": "False", "id": 198, "confidence": 0.89136}], "predicate": {"operator": "<=", "field": "00000d", "value": 119}, "count": 112, "output": "False", "id": 192, "confidence": 0.86535}], "predicate": {"operator": ">", "field": "00000f", "value": 8.39583}, "count": 143, "output": "False", "id": 190, "confidence": 0.89349}, {"objective_summary": {"categories": [["True", 2], ["False", 1]]}, "children": [{"objective_summary": {"categories": [["True", 2]]}, "predicate": {"operator": ">", "field": "00000f", "value": 8.25}, "count": 2, "output": "True", "id": 214, "confidence": 0.34237}, {"objective_summary": {"categories": [["False", 1]]}, "predicate": {"operator": "<=", "field": "00000f", "value": 8.25}, "count": 1, "output": "False", "id": 215, "confidence": 0.20654}], "predicate": {"operator": "<=", "field": "00000f", "value": 8.39583}, "count": 3, "output": "True", "id": 213, "confidence": 0.20765}], "predicate": {"operator": ">", "field": "100014", "value": 0.28495}, "count": 146, "output": "False", "id": 189, "confidence": 0.87851}, {"objective_summary": {"categories": [["False", 175], ["True", 4]]}, "children": [{"objective_summary": {"categories": [["False", 44], ["True", 4]]}, "children": [{"objective_summary": {"categories": [["False", 28]]}, "predicate": {"operator": ">", "field": "100014", "value": 0.23601}, "count": 28, "output": "False", "id": 218, "confidence": 0.87935}, {"objective_summary": {"categories": [["False", 16], ["True", 4]]}, "predicate": {"operator": "<=", "field": "100014", "value": 0.23601}, "count": 20, "output": "False", "id": 219, "confidence": 0.58398}], "predicate": {"operator": ">", "field": "000001", "value": 125}, "count": 48, "output": "False", "id": 217, "confidence": 0.80446}, {"objective_summary": {"categories": [["False", 131]]}, "predicate": {"operator": "<=", "field": "000001", "value": 125}, "count": 131, "output": "False", "id": 220, "confidence": 0.97151}], "predicate": {"operator": "<=", "field": "100014", "value": 0.28495}, "count": 179, "output": "False", "id": 216, "confidence": 0.94396}], "predicate": {"operator": ">", "field": "000001", "value": 57}, "count": 325, "output": "False", "id": 188, "confidence": 0.929}, {"objective_summary": {"categories": [["False", 54]]}, "predicate": {"operator": "<=", "field": "000001", "value": 57}, "count": 54, "output": "False", "id": 221, "confidence": 0.93358}], "predicate": {"operator": "<=", "field": "100016", "value": 0.12693}, "count": 379, "output": "False", "id": 187, "confidence": 0.93896}], "predicate": {"operator": "<=", "field": "100014", "value": 0.39172}, "count": 448, "output": "False", "id": 185, "confidence": 0.94823}], "predicate": {"operator": "<=", "field": "100014", "value": 0.41528}, "count": 455, "output": "False", "id": 181, "confidence": 0.94365}], "predicate": {"operator": "<=", "field": "000005", "value": 43}, "count": 507, "output": "False", "id": 179, "confidence": 0.94935}], "predicate": {"operator": "<=", "field": "000009", "value": 264.22054}, "count": 509, "output": "False", "id": 175, "confidence": 0.94717}], "predicate": {"operator": "<=", "field": "000006", "value": 212.11778}, "count": 584, "output": "False", "id": 173, "confidence": 0.95388}], "predicate": {"operator": ">", "field": "00000f", "value": 8.03072}, "count": 627, "output": "False", "id": 161, "confidence": 0.94745}, {"objective_summary": {"categories": [["False", 85]]}, "predicate": {"operator": "<=", "field": "00000f", "value": 8.03072}, "count": 85, "output": "False", "id": 222, "confidence": 0.95676}], "predicate": {"operator": "<=", "field": "000001", "value": 217}, "count": 712, "output": "False", "id": 160, "confidence": 0.95366}], "predicate": {"operator": ">", "field": "100017", "value": 0.41525}, "count": 713, "output": "False", "id": 158, "confidence": 0.95206}, {"objective_summary": {"categories": [["False", 171]]}, "predicate": {"operator": "<=", "field": "100017", "value": 0.41525}, "count": 171, "output": "False", "id": 223, "confidence": 0.97803}], "predicate": {"operator": "<=", "field": "000007", "value": 125}, "count": 889, "output": "False", "id": 157, "confidence": 0.96148}], "predicate": {"operator": ">", "field": "000006", "value": 115.12986}, "count": 963, "output": "False", "id": 143, "confidence": 0.95709}, {"objective_summary": {"categories": [["False", 69], ["True", 7]]}, "children": [{"objective_summary": {"categories": [["False", 41], ["True", 7]]}, "children": [{"objective_summary": {"categories": [["False", 6], ["True", 4]]}, "children": [{"objective_summary": {"categories": [["False", 6], ["True", 2]]}, "children": [{"objective_summary": {"categories": [["True", 2], ["False", 1]]}, "children": [{"objective_summary": {"categories": [["False", 1]]}, "predicate": {"operator": ">", "field": "100015", "value": 0.19708}, "count": 1, "output": "False", "id": 229, "confidence": 0.20654}, {"objective_summary": {"categories": [["True", 2]]}, "predicate": {"operator": "<=", "field": "100015", "value": 0.19708}, "count": 2, "output": "True", "id": 230, "confidence": 0.34237}], "predicate": {"operator": ">", "field": "100015", "value": 0.15577}, "count": 3, "output": "True", "id": 228, "confidence": 0.20765}, {"objective_summary": {"categories": [["False", 5]]}, "predicate": {"operator": "<=", "field": "100015", "value": 0.15577}, "count": 5, "output": "False", "id": 231, "confidence": 0.56551}], "predicate": {"operator": ">", "field": "00000c", "value": 175.35}, "count": 8, "output": "False", "id": 227, "confidence": 0.40927}, {"objective_summary": {"categories": [["True", 2]]}, "predicate": {"operator": "<=", "field": "00000c", "value": 175.35}, "count": 2, "output": "True", "id": 232, "confidence": 0.34237}], "predicate": {"operator": ">", "field": "100017", "value": 1.08167}, "count": 10, "output": "False", "id": 226, "confidence": 0.31267}, {"objective_summary": {"categories": [["False", 35], ["True", 3]]}, "children": [{"objective_summary": {"categories": [["False", 23]]}, "predicate": {"operator": ">", "field": "100014", "value": 0.17882}, "count": 23, "output": "False", "id": 234, "confidence": 0.85688}, {"objective_summary": {"categories": [["False", 12], ["True", 3]]}, "children": [{"objective_summary": {"categories": [["True", 2], ["False", 1]]}, "children": [{"objective_summary": {"categories": [["False", 1]]}, "predicate": {"operator": ">", "field": "00000c", "value": 212.7}, "count": 1, "output": "False", "id": 237, "confidence": 0.20654}, {"objective_summary": {"categories": [["True", 2]]}, "predicate": {"operator": "<=", "field": "00000c", "value": 212.7}, "count": 2, "output": "True", "id": 238, "confidence": 0.34237}], "predicate": {"operator": ">", "field": "100014", "value": 0.17485}, "count": 3, "output": "True", "id": 236, "confidence": 0.20765}, {"objective_summary": {"categories": [["False", 11], ["True", 1]]}, "predicate": {"operator": "<=", "field": "100014", "value": 0.17485}, "count": 12, "output": "False", "id": 239, "confidence": 0.64611}], "predicate": {"operator": "<=", "field": "100014", "value": 0.17882}, "count": 15, "output": "False", "id": 235, "confidence": 0.54814}], "predicate": {"operator": "<=", "field": "100017", "value": 1.08167}, "count": 38, "output": "False", "id": 233, "confidence": 0.792}], "predicate": {"operator": ">", "field": "00000a", "value": 98}, "count": 48, "output": "False", "id": 225, "confidence": 0.72833}, {"objective_summary": {"categories": [["False", 28]]}, "predicate": {"operator": "<=", "field": "00000a", "value": 98}, "count": 28, "output": "False", "id": 240, "confidence": 0.87935}], "predicate": {"operator": "<=", "field": "000006", "value": 115.12986}, "count": 76, "output": "False", "id": 224, "confidence": 0.82187}], "predicate": {"operator": ">", "field": "00000c", "value": 127.68491}, "count": 1039, "output": "False", "id": 142, "confidence": 0.95241}, {"objective_summary": {"categories": [["False", 89]]}, "predicate": {"operator": "<=", "field": "00000c", "value": 127.68491}, "count": 89, "output": "False", "id": 241, "confidence": 0.95862}], "predicate": {"operator": ">", "field": "100014", "value": 0.15749}, "count": 1128, "output": "False", "id": 141, "confidence": 0.95613}, {"objective_summary": {"categories": [["False", 105]]}, "predicate": {"operator": "<=", "field": "100014", "value": 0.15749}, "count": 105, "output": "False", "id": 242, "confidence": 0.9647}], "predicate": {"operator": "<=", "field": "000009", "value": 328.87333}, "count": 1234, "output": "False", "id": 140, "confidence": 0.95988}], "predicate": {"operator": ">", "field": "000009", "value": 168.33829}, "count": 1245, "output": "False", "id": 136, "confidence": 0.95746}, {"objective_summary": {"categories": [["False", 468], ["True", 4]]}, "children": [{"objective_summary": {"categories": [["True", 1]]}, "predicate": {"operator": ">", "field": "000005", "value": 46}, "count": 1, "output": "True", "id": 244, "confidence": 0.20654}, {"objective_summary": {"categories": [["False", 468], ["True", 3]]}, "children": [{"objective_summary": {"categories": [["False", 78], ["True", 3]]}, "children": [{"objective_summary": {"categories": [["True", 1]]}, "predicate": {"operator": ">", "field": "000010", "value": 14}, "count": 1, "output": "True", "id": 247, "confidence": 0.20654}, {"objective_summary": {"categories": [["False", 78], ["True", 2]]}, "children": [{"objective_summary": {"categories": [["False", 14], ["True", 2]]}, "children": [{"objective_summary": {"categories": [["False", 14]]}, "predicate": {"operator": ">", "field": "00000d", "value": 92}, "count": 14, "output": "False", "id": 250, "confidence": 0.78468}, {"objective_summary": {"categories": [["True", 2]]}, "predicate": {"operator": "<=", "field": "00000d", "value": 92}, "count": 2, "output": "True", "id": 251, "confidence": 0.34237}], "predicate": {"operator": ">", "field": "000005", "value": 29}, "count": 16, "output": "False", "id": 249, "confidence": 0.63977}, {"objective_summary": {"categories": [["False", 64]]}, "predicate": {"operator": "<=", "field": "000005", "value": 29}, "count": 64, "output": "False", "id": 252, "confidence": 0.94337}], "predicate": {"operator": "<=", "field": "000010", "value": 14}, "count": 80, "output": "False", "id": 248, "confidence": 0.91335}], "predicate": {"operator": ">", "field": "000007", "value": 120}, "count": 81, "output": "False", "id": 246, "confidence": 0.89668}, {"objective_summary": {"categories": [["False", 390]]}, "predicate": {"operator": "<=", "field": "000007", "value": 120}, "count": 390, "output": "False", "id": 253, "confidence": 0.99025}], "predicate": {"operator": "<=", "field": "000005", "value": 46}, "count": 471, "output": "False", "id": 245, "confidence": 0.98144}], "predicate": {"operator": "<=", "field": "000009", "value": 168.33829}, "count": 472, "output": "False", "id": 243, "confidence": 0.97841}], "predicate": {"operator": "<=", "field": "000006", "value": 220.03228}, "count": 1717, "output": "False", "id": 135, "confidence": 0.96644}], "predicate": {"operator": "=", "field": "000003", "value": "No"}, "count": 1953, "output": "False", "id": 101, "confidence": 0.95383}, {"objective_summary": {"categories": [["False", 121], ["True", 78]]}, "children": [{"objective_summary": {"categories": [["True", 47]]}, "predicate": {"operator": ">", "field": "100017", "value": 1.18006}, "count": 47, "output": "True", "id": 255, "confidence": 0.92444}, {"objective_summary": {"categories": [["False", 121], ["True", 31]]}, "children": [{"objective_summary": {"categories": [["True", 20]]}, "predicate": {"operator": ">", "field": "00000f", "value": 13.11071}, "count": 20, "output": "True", "id": 257, "confidence": 0.83887}, {"objective_summary": {"categories": [["False", 121], ["True", 11]]}, "children": [{"objective_summary": {"categories": [["False", 121], ["True", 3]]}, "children": [{"objective_summary": {"categories": [["True", 2]]}, "predicate": {"operator": ">", "field": "000009", "value": 323.15}, "count": 2, "output": "True", "id": 260, "confidence": 0.34237}, {"objective_summary": {"categories": [["False", 121], ["True", 1]]}, "children": [{"objective_summary": {"categories": [["False", 121]]}, "predicate": {"operator": ">", "field": "00000c", "value": 84.475}, "count": 121, "output": "False", "id": 262, "confidence": 0.96923}, {"objective_summary": {"categories": [["True", 1]]}, "predicate": {"operator": "<=", "field": "00000c", "value": 84.475}, "count": 1, "output": "True", "id": 263, "confidence": 0.20654}], "predicate": {"operator": "<=", "field": "000009", "value": 323.15}, "count": 122, "output": "False", "id": 261, "confidence": 0.95503}], "predicate": {"operator": ">", "field": "000010", "value": 2}, "count": 124, "output": "False", "id": 259, "confidence": 0.93128}, {"objective_summary": {"categories": [["True", 8]]}, "predicate": {"operator": "<=", "field": "000010", "value": 2}, "count": 8, "output": "True", "id": 264, "confidence": 0.67558}], "predicate": {"operator": "<=", "field": "00000f", "value": 13.11071}, "count": 132, "output": "False", "id": 258, "confidence": 0.85693}], "predicate": {"operator": "<=", "field": "100017", "value": 1.18006}, "count": 152, "output": "False", "id": 256, "confidence": 0.72507}], "predicate": {"operator": "=", "field": "000003", "value": "Yes"}, "count": 199, "output": "False", "id": 254, "confidence": 0.53878}], "predicate": {"operator": "<=", "field": "000012", "value": 3}, "count": 2152, "output": "False", "id": 100, "confidence": 0.91875}], "predicate": {"operator": "<=", "field": "000006", "value": 244.67063}, "count": 2347, "output": "False", "id": 62, "confidence": 0.87811}], "predicate": true, "count": 2665, "output": "False", "id": 0, "confidence": 0.83701}, "fields": {"000001": {"summary": {"maximum": 243, "kurtosis": -0.09777, "population": 2665, "missing_count": 0, "skewness": 0.07262, "sum_squares": 31262269, "bins": [[3.95, 20], [14, 32], [22.95122, 41], [32.45283, 53], [40.16393, 61], [46.57407, 54], [54.73529, 136], [62.71963, 107], [68.65, 120], [75.60606, 165], [83.77295, 207], [91.21023, 176], [97.98404, 188], [105.15217, 184], [112.09697, 165], [119.52381, 210], [128.01485, 202], [136.18421, 114], [142.3125, 80], [148.7234, 94], [155.91228, 57], [163.35714, 84], [172.27586, 29], [178.41667, 24], [184.0625, 16], [191.65217, 23], [199.11111, 9], [207.71429, 7], [217, 1], [224.5, 4], [232, 1], [243, 1]], "median": 101, "mean": 100.78987, "standard_deviation": 39.65697, "minimum": 1, "variance": 1572.67505, "sum": 268605, "exact_histogram": {"width": 10, "start": 0, "populations": [20, 36, 45, 67, 93, 137, 183, 211, 244, 270, 258, 244, 243, 184, 144, 89, 81, 46, 28, 23, 11, 2, 4, 1, 1]}}, "name": "Account length", "generated": false, "order": 0, "optype": "numeric", "column_number": 1, "preferred": true, "datatype": "int16"}, "100014": {"summary": {"maximum": 1.228, "kurtosis": 3.89062, "population": 2663, "missing_count": 2, "skewness": 1.17257, "sum_squares": 312.52529, "bins": [[0.029, 11], [0.0654, 12], [0.10468, 60], [0.14158, 76], [0.17078, 107], [0.19951, 193], [0.22865, 285], [0.2611, 336], [0.29191, 279], [0.32659, 383], [0.36187, 184], [0.38706, 181], [0.4144, 133], [0.44155, 76], [0.46762, 93], [0.49627, 85], [0.52684, 53], [0.55699, 39], [0.58923, 19], [0.6198, 11], [0.65416, 12], [0.69539, 9], [0.72646, 6], [0.76911, 4], [0.80315, 2], [0.83262, 3], [0.8877, 5], [0.94654, 1], [0.98534, 2], [1.072, 1], [1.10386, 1], [1.228, 1]], "median": 0.30319, "mean": 0.31896, "standard_deviation": 0.12501, "minimum": 0.00389, "variance": 0.01563, "sum": 849.3985, "exact_histogram": {"open_max": 11, "start": 0, "width": 0.05, "populations": [11, 35, 103, 212, 440, 494, 457, 349, 204, 157, 96, 44, 16, 15, 10, 5, 4]}}, "name": "Total day charge per call", "generated": true, "order": 14, "optype": "numeric", "column_number": 20, "preferred": true, "datatype": "double"}, "000006": {"summary": {"maximum": 350.8, "kurtosis": 0.03256, "population": 2665, "missing_count": 0, "skewness": -0.03304, "sum_squares": 94476015.05, "bins": [[3.66, 5], [16.53333, 3], [27.6, 3], [37.57778, 9], [50.24, 15], [60.81429, 21], [72.9125, 32], [85.88868, 53], [98.66494, 77], [111.50194, 103], [122.92315, 108], [133.03953, 129], [142.36507, 146], [150.59236, 157], [158.69235, 170], [168.44551, 178], [179.48186, 226], [193.05309, 275], [204.93146, 178], [214.97716, 162], [223.6, 131], [236.41543, 162], [248.97349, 83], [260.43043, 69], [270.15833, 60], [279.28158, 38], [288.692, 25], [299.48421, 19], [311.125, 12], [322.7125, 8], [332.12, 5], [347.63333, 3]], "median": 179.9, "mean": 180.20424, "standard_deviation": 54.57299, "minimum": 0, "variance": 2978.21167, "sum": 480244.3, "exact_histogram": {"width": 20, "start": 0, "populations": [8, 9, 25, 46, 98, 163, 241, 378, 366, 381, 335, 255, 151, 122, 50, 22, 12, 3]}}, "name": "Total day minutes", "generated": false, "order": 4, "optype": "numeric", "column_number": 6, "preferred": true, "datatype": "double"}, "000003": {"summary": {"categories": [["No", 2408], ["Yes", 257]], "missing_count": 0}, "name": "International plan", "generated": false, "order": 2, "optype": "categorical", "column_number": 3, "preferred": true, "term_analysis": {"enabled": true}, "datatype": "string"}, "000007": {"summary": {"maximum": 165, "kurtosis": 0.4241, "population": 2665, "missing_count": 0, "skewness": -0.12773, "sum_squares": 27955451, "bins": [[0, 2], [30, 1], [35.5, 2], [41, 4], [45.625, 8], [50.5, 4], [54, 17], [57.38095, 21], [61.37931, 29], [66.1129, 62], [72.05263, 114], [78.15484, 155], [82.58594, 128], [86.04, 125], [89.43316, 187], [93.54, 200], [97.47208, 197], [101.4, 215], [105.04651, 172], [108.43458, 214], [113.0093, 215], [117.36601, 153], [120.95833, 96], [124.37143, 105], [129.17045, 88], [133.83019, 53], [138.65, 40], [142.17647, 17], [146.28571, 21], [150.5, 12], [157.83333, 6], [164, 2]], "median": 101, "mean": 100.44916, "standard_deviation": 19.99919, "minimum": 0, "variance": 399.96748, "sum": 267697, "exact_histogram": {"open_min": 5, "start": 40, "width": 5, "populations": [7, 6, 13, 28, 36, 66, 92, 130, 164, 225, 234, 250, 266, 282, 232, 189, 154, 98, 76, 41, 30, 22, 11, 5, 2, 1]}}, "name": "Total day calls", "generated": false, "order": 5, "optype": "numeric", "column_number": 7, "preferred": true, "datatype": "int16"}, "000005": {"summary": {"maximum": 51, "kurtosis": -0.0892, "population": 2665, "missing_count": 0, "skewness": 1.24897, "sum_squares": 669079, "bins": [[0, 1922], [4, 1], [9, 1], [11, 2], [12.44444, 9], [14.53333, 15], [16.41176, 17], [18.70833, 24], [20.60465, 43], [22.54237, 59], [24.50769, 65], [26.51471, 68], [28.55682, 88], [30.58427, 89], [32.51471, 68], [34, 21], [35, 26], [36, 26], [37, 21], [38, 16], [39, 23], [40, 14], [41, 9], [42, 8], [43, 9], [44, 6], [45, 5], [46, 4], [47, 3], [48, 1], [49, 1], [51, 1]], "median": 0, "mean": 8.10769, "standard_deviation": 13.61604, "minimum": 0, "variance": 185.39643, "sum": 21607, "exact_histogram": {"width": 2, "start": 0, "populations": [1922, 0, 1, 0, 1, 2, 9, 15, 17, 24, 43, 59, 65, 68, 88, 89, 68, 47, 47, 39, 23, 17, 11, 7, 2, 1]}}, "name": "Number vmail messages", "generated": false, "order": 3, "optype": "numeric", "column_number": 5, "preferred": true, "datatype": "int8"}, "100015": {"summary": {"maximum": 1.32667, "kurtosis": 36.06148, "population": 2664, "missing_count": 1, "skewness": 2.84391, "sum_squares": 96.04026, "bins": [[0.02304, 1], [0.04345, 10], [0.06347, 31], [0.08115, 72], [0.09871, 137], [0.11533, 195], [0.13196, 260], [0.14904, 414], [0.1658, 285], [0.17834, 230], [0.19178, 232], [0.20579, 155], [0.21902, 153], [0.23472, 143], [0.2477, 67], [0.26243, 74], [0.27857, 71], [0.29943, 33], [0.31574, 36], [0.33344, 17], [0.34917, 12], [0.3621, 9], [0.37481, 5], [0.39456, 9], [0.41397, 2], [0.42497, 3], [0.43809, 1], [0.4737, 1], [0.4884, 2], [0.50306, 1], [0.52882, 2], [1.32667, 1]], "median": 0.16864, "mean": 0.17811, "standard_deviation": 0.0658, "minimum": 0.02304, "variance": 0.00433, "sum": 474.48777, "exact_histogram": {"open_max": 11, "start": 0.02, "width": 0.02, "populations": [2, 16, 58, 123, 201, 317, 418, 419, 317, 243, 181, 117, 90, 46, 40, 29, 14, 10, 7, 5]}}, "name": "Total eve charge per call", "generated": true, "order": 15, "optype": "numeric", "column_number": 21, "preferred": true, "datatype": "double"}, "000013": {"summary": {"categories": [["False", 2268], ["True", 397]], "missing_count": 0}, "name": "Churn", "generated": false, "order": 13, "optype": "categorical", "column_number": 19, "preferred": true, "term_analysis": {"enabled": true}, "datatype": "string"}, "100017": {"summary": {"maximum": 4.91, "kurtosis": 6.49513, "population": 2649, "missing_count": 16, "skewness": 2.24079, "sum_squares": 2909.95915, "bins": [[0.12635, 28], [0.2333, 158], [0.36432, 390], [0.48275, 322], [0.58334, 318], [0.68347, 266], [0.79118, 222], [0.89213, 168], [1.01276, 187], [1.15238, 120], [1.26145, 78], [1.38439, 63], [1.49686, 70], [1.62403, 50], [1.74951, 41], [1.87352, 27], [1.99412, 17], [2.14706, 17], [2.315, 2], [2.44, 16], [2.576, 10], [2.68813, 16], [2.92, 12], [3.12375, 8], [3.23286, 7], [3.34917, 12], [3.48615, 13], [3.62, 1], [3.75, 1], [3.96, 5], [4.13, 3], [4.91, 1]], "median": 0.675, "mean": 0.84855, "standard_deviation": 0.61532, "minimum": 0.05833, "variance": 0.37862, "sum": 2247.81353, "exact_histogram": {"open_max": 11, "start": 0, "width": 0.2, "populations": [62, 419, 616, 522, 321, 226, 133, 105, 77, 36, 24, 5, 23, 17, 10, 11, 17, 14]}}, "name": "Total intl charge per call", "generated": true, "order": 17, "optype": "numeric", "column_number": 23, "preferred": true, "datatype": "double"}, "000012": {"summary": {"counts": [[0, 559], [1, 939], [2, 602], [3, 347], [4, 132], [5, 60], [6, 17], [7, 6], [8, 2], [9, 1]], "maximum": 9, "kurtosis": 1.47734, "population": 2665, "missing_count": 0, "skewness": 1.05218, "sum_squares": 11197, "median": 1, "mean": 1.56886, "standard_deviation": 1.31941, "minimum": 0, "variance": 1.74085, "sum": 4181, "exact_histogram": {"width": 1, "start": 0, "populations": [559, 939, 602, 347, 132, 60, 17, 6, 2, 1]}}, "name": "Customer service calls", "generated": false, "order": 12, "optype": "numeric", "column_number": 18, "preferred": true, "datatype": "int8"}, "00000a": {"summary": {"maximum": 170, "kurtosis": 0.28372, "population": 2665, "missing_count": 0, "skewness": -0.06153, "sum_squares": 27908335, "bins": [[0, 1], [12, 1], [36.5, 2], [42.5, 2], [47.11111, 9], [50.90909, 11], [54.92857, 14], [59.27586, 29], [64.02222, 45], [67.90625, 64], [73.02105, 95], [78.57738, 168], [83.52667, 150], [88.34296, 277], [93.08649, 185], [97.64364, 275], [102.48276, 203], [106.46078, 204], [110.26316, 190], [113.99379, 161], [117.51034, 145], [121.51538, 130], [126.01869, 107], [131.01515, 66], [136.5303, 66], [142.37931, 29], [147.47059, 17], [151.6, 10], [155.4, 5], [159, 1], [164, 1], [169, 2]], "median": 101, "mean": 100.3651, "standard_deviation": 19.97915, "minimum": 0, "variance": 399.16657, "sum": 267473, "exact_histogram": {"open_min": 6, "start": 45, "width": 5, "populations": [9, 17, 24, 39, 73, 89, 127, 172, 232, 251, 245, 247, 262, 237, 201, 145, 106, 64, 50, 33, 17, 11, 5, 1, 1, 1]}}, "name": "Total eve calls", "generated": false, "order": 7, "optype": "numeric", "column_number": 10, "preferred": true, "datatype": "int16"}, "000002": {"summary": {"counts": [[408, 674], [415, 1331], [510, 660]], "maximum": 510, "kurtosis": -0.64511, "population": 2665, "missing_count": 0, "skewness": 1.15287, "sum_squares": 513094211, "median": 415, "mean": 436.75685, "standard_deviation": 42.12817, "minimum": 408, "variance": 1774.78245, "sum": 1163957, "exact_histogram": {"width": 50, "start": 400, "populations": [2005, 0, 660]}}, "name": "Area code", "generated": false, "order": 1, "optype": "numeric", "column_number": 2, "preferred": true, "datatype": "int16"}, "00000f": {"summary": {"maximum": 20, "kurtosis": 0.66298, "population": 2665, "missing_count": 0, "skewness": -0.23815, "sum_squares": 300781.09, "bins": [[0, 16], [1.2, 2], [2.225, 4], [3.1, 5], [3.73333, 9], [4.15625, 16], [4.69524, 21], [5.26818, 44], [5.815, 60], [6.29298, 57], [6.75455, 77], [7.36593, 135], [7.88305, 118], [8.35455, 121], [8.80063, 158], [9.35556, 234], [10.01978, 278], [10.6, 177], [11.14803, 254], [11.74646, 198], [12.4, 203], [13.09605, 177], [13.84113, 124], [14.59714, 70], [15.33542, 48], [15.97368, 19], [16.47333, 15], [16.97143, 7], [17.42222, 9], [18.07143, 7], [18.9, 1], [20, 1]], "median": 10.3, "mean": 10.25152, "standard_deviation": 2.78796, "minimum": 0, "variance": 7.77271, "sum": 27320.3, "exact_histogram": {"width": 1, "start": 0, "populations": [16, 2, 6, 13, 36, 94, 134, 221, 297, 358, 401, 373, 287, 205, 110, 62, 28, 14, 7, 0, 1]}}, "name": "Total intl minutes", "generated": false, "order": 10, "optype": "numeric", "column_number": 15, "preferred": true, "datatype": "double"}, "000009": {"summary": {"maximum": 363.7, "kurtosis": 0.04987, "population": 2665, "missing_count": 0, "skewness": -0.03984, "sum_squares": 114380325.47, "bins": [[0, 1], [31.2, 1], [44.45, 4], [58.94286, 7], [67.97143, 7], [79, 16], [90.15217, 23], [103.41724, 29], [113.4641, 39], [122.00857, 70], [133.07021, 94], [144.15652, 115], [154.25379, 132], [166.51338, 269], [178.45814, 172], [187.55127, 158], [195.47469, 162], [203.48581, 155], [211.66927, 192], [222.99779, 272], [235.4057, 158], [245.62027, 148], [256.41591, 132], [266.94528, 106], [277.57222, 72], [289.72034, 59], [302.61786, 28], [315.9, 21], [328.7, 11], [338.225, 4], [350.5, 6], [362.75, 2]], "median": 201, "mean": 200.80409, "standard_deviation": 50.97194, "minimum": 0, "variance": 2598.13903, "sum": 535142.9, "exact_histogram": {"width": 20, "start": 0, "populations": [1, 1, 8, 18, 37, 84, 153, 245, 375, 384, 412, 346, 271, 181, 84, 38, 18, 7, 2]}}, "name": "Total eve minutes", "generated": false, "order": 6, "optype": "numeric", "column_number": 9, "preferred": true, "datatype": "double"}, "00000d": {"summary": {"maximum": 175, "kurtosis": -0.0914, "population": 2665, "missing_count": 0, "skewness": 0.01382, "sum_squares": 27680818, "bins": [[37, 2], [42, 2], [49.14286, 7], [53.69231, 13], [57.07143, 14], [60.46875, 32], [63.83784, 37], [67.55357, 56], [71.1, 50], [74.60714, 112], [78.53043, 115], [82.52414, 145], [86.55705, 149], [90.53266, 199], [94.57547, 212], [98.59113, 203], [103.18375, 283], [107.39785, 186], [111.5, 174], [114.94309, 123], [118.08943, 123], [122.14857, 175], [126.5, 70], [130.05556, 54], [133.24324, 37], [137.45, 40], [141.3125, 16], [145.77778, 18], [151.72727, 11], [157, 4], [165, 2], [175, 1]], "median": 100, "mean": 100.02777, "standard_deviation": 19.52914, "minimum": 36, "variance": 381.38737, "sum": 266574, "exact_histogram": {"width": 5, "start": 35, "populations": [2, 2, 4, 12, 24, 53, 66, 100, 147, 175, 199, 252, 257, 273, 252, 216, 195, 172, 99, 68, 44, 20, 15, 11, 4, 1, 1, 0, 1]}}, "name": "Total night calls", "generated": false, "order": 9, "optype": "numeric", "column_number": 13, "preferred": true, "datatype": "int16"}, "000010": {"summary": {"counts": [[0, 16], [1, 136], [2, 391], [3, 538], [4, 493], [5, 379], [6, 266], [7, 160], [8, 92], [9, 91], [10, 38], [11, 25], [12, 11], [13, 13], [14, 5], [15, 4], [16, 2], [17, 1], [18, 2], [19, 1], [20, 1]], "maximum": 20, "kurtosis": 3.12373, "population": 2665, "missing_count": 0, "skewness": 1.33469, "sum_squares": 69276, "median": 4, "mean": 4.45779, "standard_deviation": 2.47491, "minimum": 0, "variance": 6.12519, "sum": 11880, "exact_histogram": {"width": 1, "start": 0, "populations": [16, 136, 391, 538, 493, 379, 266, 160, 92, 91, 38, 25, 11, 13, 5, 4, 2, 1, 2, 1, 1]}}, "name": "Total intl calls", "generated": false, "order": 11, "optype": "numeric", "column_number": 16, "preferred": true, "datatype": "int8"}, "100016": {"summary": {"maximum": 0.27806, "kurtosis": 1.66117, "population": 2665, "missing_count": 0, "skewness": 0.88264, "sum_squares": 26.16561, "bins": [[0.0102, 1], [0.01726, 3], [0.02537, 9], [0.03514, 32], [0.04268, 58], [0.05051, 102], [0.05675, 103], [0.0627, 155], [0.069, 202], [0.07702, 343], [0.0861, 341], [0.09278, 207], [0.09855, 187], [0.10453, 184], [0.11067, 139], [0.11651, 121], [0.12532, 164], [0.13493, 66], [0.14178, 72], [0.14908, 49], [0.15721, 46], [0.1663, 26], [0.17331, 6], [0.17934, 8], [0.18668, 16], [0.19723, 11], [0.20346, 1], [0.21174, 3], [0.22396, 6], [0.23898, 2], [0.24681, 1], [0.27806, 1]], "median": 0.08979, "mean": 0.09381, "standard_deviation": 0.0319, "minimum": 0.0102, "variance": 0.00102, "sum": 250.01519, "exact_histogram": {"open_max": 12, "start": 0.01, "width": 0.01, "populations": [4, 9, 37, 95, 171, 277, 350, 395, 356, 293, 205, 143, 102, 82, 56, 34, 12, 18, 9, 5]}}, "name": "Total night charge per call", "generated": true, "order": 16, "optype": "numeric", "column_number": 22, "preferred": true, "datatype": "double"}, "00000c": {"summary": {"maximum": 395, "kurtosis": 0.06977, "population": 2665, "missing_count": 0, "skewness": -0.02582, "sum_squares": 113414812.95, "bins": [[23.2, 1], [47.26, 5], [55.18, 5], [66.35, 6], [76.7, 18], [87.3, 10], [100.69783, 46], [111.78837, 43], [121.05, 54], [130.78947, 76], [139.19296, 71], [147.74052, 116], [156.56045, 134], [169.23249, 277], [181.7601, 193], [192.60077, 260], [203.4213, 169], [212.7875, 200], [225.65747, 308], [238.23047, 128], [246.60153, 131], [256.60444, 135], [268.12222, 108], [282.07187, 64], [291.1875, 40], [300.80952, 21], [310.685, 20], [323.48462, 13], [333.7, 2], [348.3375, 8], [366.3, 2], [395, 1]], "median": 199.7, "mean": 199.99583, "standard_deviation": 50.59426, "minimum": 23.2, "variance": 2559.77962, "sum": 532988.9, "exact_histogram": {"width": 20, "start": 20, "populations": [1, 10, 21, 32, 89, 151, 259, 361, 411, 385, 361, 279, 150, 98, 33, 13, 8, 2, 1]}}, "name": "Total night minutes", "generated": false, "order": 8, "optype": "numeric", "column_number": 12, "preferred": true, "datatype": "double"}}, "depth_threshold": 512, "node_threshold": 512}, "credits_per_prediction": 0.0, "source": "source/5b968a2cc7736e657b001acd", "source_status": true, "randomize": false, "number_of_public_predictions": 0, "support_threshold": 0.0, "price": 0.0, "input_fields": ["000001", "000002", "000003", "000005", "000006", "000007", "000009", "00000a", "00000c", "00000d", "00000f", "000010", "000012", "100014", "100015", "100016", "100017"], "project": "project/5b96893f92527314e1001dd9", "fields_meta": {"query_total": 18, "total": 18, "count": 18, "offset": 0, "limit": 1000}, "boosting": {}, "ensemble_id": "", "max_columns": 24, "objective_field_name": "Churn", "resource": "model/5b968a782774cb43ca00020d", "stat_pruning": true, "objective_field_type": "categorical", "replacement": false, "ensemble_index": 0, "white_box": false, "excluded_fields": ["Total day charge", "Total eve charge", "Total night charge", "Total intl charge"], "node_threshold": 512, "operating_point": {}}}